{"ver":1,"sampleRate":100,"tags":{"ai.application.ver":"unknown","ai.device.id":"","ai.cloud.roleInstance":"shashwatmdas-Predator-PH315-51","ai.device.osVersion":"Linux 4.15.0-91-generic","ai.cloud.role":"Web","ai.device.osArchitecture":"x64","ai.device.osPlatform":"linux","ai.internal.sdkVersion":"node:2020.2.64397"},"data":{"baseType":"EventData","baseData":{"ver":2,"properties":{"common.os":"linux","common.platformversion":"4.15.0","common.extname":"ms-python.python","common.extversion":"2020.2.64397","common.vscodemachineid":"0368571be9af00be63ebb6f48d839834b0e7616b807d0be78a5ef4bb335361e6","common.vscodesessionid":"60074dd9-2ee2-4210-870e-77d96679a5291591092739112","common.vscodeversion":"1.38.1"},"measurements":{"duration":32},"name":"ms-python.python/SIGNATURE"}},"iKey":"AIF-d9b70cd4-b9f9-4d70-929b-a071c400b217","name":"Microsoft.ApplicationInsights.AIFd9b70cd4b9f94d70929ba071c400b217.Event","time":"2020-06-02T10:15:55.572Z"}
{"ver":1,"sampleRate":100,"tags":{"ai.application.ver":"unknown","ai.device.id":"","ai.cloud.roleInstance":"shashwatmdas-Predator-PH315-51","ai.device.osVersion":"Linux 4.15.0-91-generic","ai.cloud.role":"Web","ai.device.osArchitecture":"x64","ai.device.osPlatform":"linux","ai.internal.sdkVersion":"node:2020.2.64397"},"data":{"baseType":"EventData","baseData":{"ver":2,"properties":{"common.os":"linux","common.platformversion":"4.15.0","common.extname":"ms-python.python","common.extversion":"2020.2.64397","common.vscodemachineid":"0368571be9af00be63ebb6f48d839834b0e7616b807d0be78a5ef4bb335361e6","common.vscodesessionid":"60074dd9-2ee2-4210-870e-77d96679a5291591092739112","common.vscodeversion":"1.38.1"},"measurements":{"duration":57},"name":"ms-python.python/COMPLETION"}},"iKey":"AIF-d9b70cd4-b9f9-4d70-929b-a071c400b217","name":"Microsoft.ApplicationInsights.AIFd9b70cd4b9f94d70929ba071c400b217.Event","time":"2020-06-02T10:15:55.697Z"}
{"ver":1,"sampleRate":100,"tags":{"ai.application.ver":"unknown","ai.device.id":"","ai.cloud.roleInstance":"shashwatmdas-Predator-PH315-51","ai.device.osVersion":"Linux 4.15.0-91-generic","ai.cloud.role":"Web","ai.device.osArchitecture":"x64","ai.device.osPlatform":"linux","ai.internal.sdkVersion":"node:2020.2.64397"},"data":{"baseType":"EventData","baseData":{"ver":2,"properties":{"common.os":"linux","common.platformversion":"4.15.0","common.extname":"ms-python.python","common.extversion":"2020.2.64397","common.vscodemachineid":"0368571be9af00be63ebb6f48d839834b0e7616b807d0be78a5ef4bb335361e6","common.vscodesessionid":"60074dd9-2ee2-4210-870e-77d96679a5291591092739112","common.vscodeversion":"1.38.1"},"measurements":{"duration":59},"name":"ms-python.python/COMPLETION"}},"iKey":"AIF-d9b70cd4-b9f9-4d70-929b-a071c400b217","name":"Microsoft.ApplicationInsights.AIFd9b70cd4b9f94d70929ba071c400b217.Event","time":"2020-06-02T10:15:56.895Z"}
{"ver":1,"sampleRate":100,"tags":{"ai.application.ver":"unknown","ai.device.id":"","ai.cloud.roleInstance":"shashwatmdas-Predator-PH315-51","ai.device.osVersion":"Linux 4.15.0-91-generic","ai.cloud.role":"Web","ai.device.osArchitecture":"x64","ai.device.osPlatform":"linux","ai.internal.sdkVersion":"node:2020.2.64397"},"data":{"baseType":"EventData","baseData":{"ver":2,"properties":{"common.os":"linux","common.platformversion":"4.15.0","common.extname":"ms-python.python","common.extversion":"2020.2.64397","common.vscodemachineid":"0368571be9af00be63ebb6f48d839834b0e7616b807d0be78a5ef4bb335361e6","common.vscodesessionid":"60074dd9-2ee2-4210-870e-77d96679a5291591092739112","common.vscodeversion":"1.38.1"},"measurements":{"duration":30},"name":"ms-python.python/COMPLETION"}},"iKey":"AIF-d9b70cd4-b9f9-4d70-929b-a071c400b217","name":"Microsoft.ApplicationInsights.AIFd9b70cd4b9f94d70929ba071c400b217.Event","time":"2020-06-02T10:15:58.999Z"}
{"ver":1,"sampleRate":100,"tags":{"ai.application.ver":"unknown","ai.device.id":"","ai.cloud.roleInstance":"shashwatmdas-Predator-PH315-51","ai.device.osVersion":"Linux 4.15.0-91-generic","ai.cloud.role":"Web","ai.device.osArchitecture":"x64","ai.device.osPlatform":"linux","ai.internal.sdkVersion":"node:2020.2.64397"},"data":{"baseType":"EventData","baseData":{"ver":2,"properties":{"common.os":"linux","common.platformversion":"4.15.0","common.extname":"ms-python.python","common.extversion":"2020.2.64397","common.vscodemachineid":"0368571be9af00be63ebb6f48d839834b0e7616b807d0be78a5ef4bb335361e6","common.vscodesessionid":"60074dd9-2ee2-4210-870e-77d96679a5291591092739112","common.vscodeversion":"1.38.1"},"measurements":{"duration":58},"name":"ms-python.python/COMPLETION"}},"iKey":"AIF-d9b70cd4-b9f9-4d70-929b-a071c400b217","name":"Microsoft.ApplicationInsights.AIFd9b70cd4b9f94d70929ba071c400b217.Event","time":"2020-06-02T10:15:59.361Z"}
{"ver":1,"sampleRate":100,"tags":{"ai.application.ver":"unknown","ai.device.id":"","ai.cloud.roleInstance":"shashwatmdas-Predator-PH315-51","ai.device.osVersion":"Linux 4.15.0-91-generic","ai.cloud.role":"Web","ai.device.osArchitecture":"x64","ai.device.osPlatform":"linux","ai.internal.sdkVersion":"node:2020.2.64397"},"data":{"baseType":"EventData","baseData":{"ver":2,"properties":{"common.os":"linux","common.platformversion":"4.15.0","common.extname":"ms-python.python","common.extversion":"2020.2.64397","common.vscodemachineid":"0368571be9af00be63ebb6f48d839834b0e7616b807d0be78a5ef4bb335361e6","common.vscodesessionid":"60074dd9-2ee2-4210-870e-77d96679a5291591092739112","common.vscodeversion":"1.38.1"},"measurements":{"duration":38},"name":"ms-python.python/COMPLETION"}},"iKey":"AIF-d9b70cd4-b9f9-4d70-929b-a071c400b217","name":"Microsoft.ApplicationInsights.AIFd9b70cd4b9f94d70929ba071c400b217.Event","time":"2020-06-02T10:16:00.178Z"}
{"ver":1,"sampleRate":100,"tags":{"ai.application.ver":"unknown","ai.device.id":"","ai.cloud.roleInstance":"shashwatmdas-Predator-PH315-51","ai.device.osVersion":"Linux 4.15.0-91-generic","ai.cloud.role":"Web","ai.device.osArchitecture":"x64","ai.device.osPlatform":"linux","ai.internal.sdkVersion":"node:2020.2.64397"},"data":{"baseType":"EventData","baseData":{"ver":2,"properties":{"common.os":"linux","common.platformversion":"4.15.0","common.extname":"ms-python.python","common.extversion":"2020.2.64397","common.vscodemachineid":"0368571be9af00be63ebb6f48d839834b0e7616b807d0be78a5ef4bb335361e6","common.vscodesessionid":"60074dd9-2ee2-4210-870e-77d96679a5291591092739112","common.vscodeversion":"1.38.1"},"measurements":{"duration":34},"name":"ms-python.python/COMPLETION"}},"iKey":"AIF-d9b70cd4-b9f9-4d70-929b-a071c400b217","name":"Microsoft.ApplicationInsights.AIFd9b70cd4b9f94d70929ba071c400b217.Event","time":"2020-06-02T10:16:00.373Z"}
{"ver":1,"sampleRate":100,"tags":{"ai.application.ver":"unknown","ai.device.id":"","ai.cloud.roleInstance":"shashwatmdas-Predator-PH315-51","ai.device.osVersion":"Linux 4.15.0-91-generic","ai.cloud.role":"Web","ai.device.osArchitecture":"x64","ai.device.osPlatform":"linux","ai.internal.sdkVersion":"node:2020.2.64397"},"data":{"baseType":"EventData","baseData":{"ver":2,"properties":{"common.os":"linux","common.platformversion":"4.15.0","common.extname":"ms-python.python","common.extversion":"2020.2.64397","common.vscodemachineid":"0368571be9af00be63ebb6f48d839834b0e7616b807d0be78a5ef4bb335361e6","common.vscodesessionid":"60074dd9-2ee2-4210-870e-77d96679a5291591092739112","common.vscodeversion":"1.38.1"},"measurements":{"duration":29},"name":"ms-python.python/COMPLETION"}},"iKey":"AIF-d9b70cd4-b9f9-4d70-929b-a071c400b217","name":"Microsoft.ApplicationInsights.AIFd9b70cd4b9f94d70929ba071c400b217.Event","time":"2020-06-02T10:16:00.533Z"}
{"ver":1,"sampleRate":100,"tags":{"ai.application.ver":"unknown","ai.device.id":"","ai.cloud.roleInstance":"shashwatmdas-Predator-PH315-51","ai.device.osVersion":"Linux 4.15.0-91-generic","ai.cloud.role":"Web","ai.device.osArchitecture":"x64","ai.device.osPlatform":"linux","ai.internal.sdkVersion":"node:2020.2.64397"},"data":{"baseType":"EventData","baseData":{"ver":2,"properties":{"common.os":"linux","common.platformversion":"4.15.0","common.extname":"ms-python.python","common.extversion":"2020.2.64397","common.vscodemachineid":"0368571be9af00be63ebb6f48d839834b0e7616b807d0be78a5ef4bb335361e6","common.vscodesessionid":"60074dd9-2ee2-4210-870e-77d96679a5291591092739112","common.vscodeversion":"1.38.1"},"measurements":{"duration":28},"name":"ms-python.python/COMPLETION"}},"iKey":"AIF-d9b70cd4-b9f9-4d70-929b-a071c400b217","name":"Microsoft.ApplicationInsights.AIFd9b70cd4b9f94d70929ba071c400b217.Event","time":"2020-06-02T10:16:00.691Z"}
{"ver":1,"sampleRate":100,"tags":{"ai.application.ver":"unknown","ai.device.id":"","ai.cloud.roleInstance":"shashwatmdas-Predator-PH315-51","ai.device.osVersion":"Linux 4.15.0-91-generic","ai.cloud.role":"Web","ai.device.osArchitecture":"x64","ai.device.osPlatform":"linux","ai.internal.sdkVersion":"node:2020.2.64397"},"data":{"baseType":"EventData","baseData":{"ver":2,"properties":{"mem_use":"39284736","limit":"1073741824","isUserDefinedLimit":"false","restart":"false","common.os":"linux","common.platformversion":"4.15.0","common.extname":"ms-python.python","common.extversion":"2020.2.64397","common.vscodemachineid":"0368571be9af00be63ebb6f48d839834b0e7616b807d0be78a5ef4bb335361e6","common.vscodesessionid":"60074dd9-2ee2-4210-870e-77d96679a5291591092739112","common.vscodeversion":"1.38.1"},"name":"ms-python.python/JEDI_MEMORY"}},"iKey":"AIF-d9b70cd4-b9f9-4d70-929b-a071c400b217","name":"Microsoft.ApplicationInsights.AIFd9b70cd4b9f94d70929ba071c400b217.Event","time":"2020-06-02T10:16:02.138Z"}
{"ver":1,"sampleRate":100,"tags":{"ai.application.ver":"unknown","ai.device.id":"","ai.cloud.roleInstance":"shashwatmdas-Predator-PH315-51","ai.device.osVersion":"Linux 4.15.0-91-generic","ai.cloud.role":"Web","ai.device.osArchitecture":"x64","ai.device.osPlatform":"linux","ai.internal.sdkVersion":"node:2020.2.64397"},"data":{"baseType":"EventData","baseData":{"ver":2,"properties":{"common.os":"linux","common.platformversion":"4.15.0","common.extname":"ms-python.python","common.extversion":"2020.2.64397","common.vscodemachineid":"0368571be9af00be63ebb6f48d839834b0e7616b807d0be78a5ef4bb335361e6","common.vscodesessionid":"60074dd9-2ee2-4210-870e-77d96679a5291591092739112","common.vscodeversion":"1.38.1"},"measurements":{"duration":41},"name":"ms-python.python/COMPLETION"}},"iKey":"AIF-d9b70cd4-b9f9-4d70-929b-a071c400b217","name":"Microsoft.ApplicationInsights.AIFd9b70cd4b9f94d70929ba071c400b217.Event","time":"2020-06-02T10:16:06.638Z"}
{"ver":1,"sampleRate":100,"tags":{"ai.application.ver":"unknown","ai.device.id":"","ai.cloud.roleInstance":"shashwatmdas-Predator-PH315-51","ai.device.osVersion":"Linux 4.15.0-91-generic","ai.cloud.role":"Web","ai.device.osArchitecture":"x64","ai.device.osPlatform":"linux","ai.internal.sdkVersion":"node:2020.2.64397"},"data":{"baseType":"EventData","baseData":{"ver":2,"properties":{"common.os":"linux","common.platformversion":"4.15.0","common.extname":"ms-python.python","common.extversion":"2020.2.64397","common.vscodemachineid":"0368571be9af00be63ebb6f48d839834b0e7616b807d0be78a5ef4bb335361e6","common.vscodesessionid":"60074dd9-2ee2-4210-870e-77d96679a5291591092739112","common.vscodeversion":"1.38.1"},"measurements":{"duration":40},"name":"ms-python.python/COMPLETION"}},"iKey":"AIF-d9b70cd4-b9f9-4d70-929b-a071c400b217","name":"Microsoft.ApplicationInsights.AIFd9b70cd4b9f94d70929ba071c400b217.Event","time":"2020-06-02T10:16:08.766Z"}