{"ver":1,"sampleRate":100,"tags":{"ai.application.ver":"1.38.1","ai.device.id":"","ai.cloud.roleInstance":"shashwatmdas-Predator-PH315-51","ai.device.osVersion":"Linux 4.15.0-91-generic","ai.cloud.role":"Web","ai.device.osArchitecture":"x64","ai.device.osPlatform":"linux","ai.internal.sdkVersion":"node:1.0.8"},"data":{"baseType":"EventData","baseData":{"ver":2,"properties":{"reason":"startFileSearch","type":"searchProcess","scheme":"file","common.machineId":"0368571be9af00be63ebb6f48d839834b0e7616b807d0be78a5ef4bb335361e6","sessionID":"92b4fe55-3122-4699-8e2e-2147a39150ce1591100246759","commitHash":"b37e54c98e1a74ba89e03073e5a3761284e3ffb0","version":"1.38.1","common.platformVersion":"4.15.0","common.platform":"Linux","common.nodePlatform":"linux","common.nodeArch":"x64","common.product":"desktop","timestamp":"2020-06-02T12:19:27.974Z","common.version.shell":"4.2.10","common.version.renderer":"69.0.3497.128","common.firstSessionDate":"Sun, 29 Sep 2019 23:51:46 GMT","common.lastSessionDate":"Tue, 02 Jun 2020 09:24:03 GMT","common.isNewSession":"0","common.instanceId":"319b87fd-1aa0-48b3-b0c7-882d6bc7cdb8","common.remoteAuthority":"none"},"measurements":{"resultCount":0,"workspaceFolderCount":1,"endToEndTime":105031,"fileWalkTime":103029,"directoriesWalked":0,"filesWalked":0,"cmdTime":103028,"cmdResultCount":0,"common.timesincesessionstart":121215,"common.sequence":49},"name":"monacoworkbench/searchComplete"}},"iKey":"AIF-444c3af9-8e69-4462-ab49-4191e6ad1916","name":"Microsoft.ApplicationInsights.AIF444c3af98e694462ab494191e6ad1916.Event","time":"2020-06-02T12:19:27.974Z"}
{"ver":1,"sampleRate":100,"tags":{"ai.application.ver":"1.38.1","ai.device.id":"","ai.cloud.roleInstance":"shashwatmdas-Predator-PH315-51","ai.device.osVersion":"Linux 4.15.0-91-generic","ai.cloud.role":"Web","ai.device.osArchitecture":"x64","ai.device.osPlatform":"linux","ai.internal.sdkVersion":"node:1.0.8"},"data":{"baseType":"EventData","baseData":{"ver":2,"properties":{"reason":"startFileSearch","type":"searchProcess","scheme":"file","common.machineId":"0368571be9af00be63ebb6f48d839834b0e7616b807d0be78a5ef4bb335361e6","sessionID":"92b4fe55-3122-4699-8e2e-2147a39150ce1591100246759","commitHash":"b37e54c98e1a74ba89e03073e5a3761284e3ffb0","version":"1.38.1","common.platformVersion":"4.15.0","common.platform":"Linux","common.nodePlatform":"linux","common.nodeArch":"x64","common.product":"desktop","timestamp":"2020-06-02T12:19:27.980Z","common.version.shell":"4.2.10","common.version.renderer":"69.0.3497.128","common.firstSessionDate":"Sun, 29 Sep 2019 23:51:46 GMT","common.lastSessionDate":"Tue, 02 Jun 2020 09:24:03 GMT","common.isNewSession":"0","common.instanceId":"319b87fd-1aa0-48b3-b0c7-882d6bc7cdb8","common.remoteAuthority":"none"},"measurements":{"resultCount":47,"workspaceFolderCount":1,"endToEndTime":105037,"fileWalkTime":102389,"directoriesWalked":0,"filesWalked":0,"cmdTime":102389,"cmdResultCount":47,"common.timesincesessionstart":121221,"common.sequence":50},"name":"monacoworkbench/searchComplete"}},"iKey":"AIF-444c3af9-8e69-4462-ab49-4191e6ad1916","name":"Microsoft.ApplicationInsights.AIF444c3af98e694462ab494191e6ad1916.Event","time":"2020-06-02T12:19:27.981Z"}
{"ver":1,"sampleRate":100,"tags":{"ai.application.ver":"1.38.1","ai.device.id":"","ai.cloud.roleInstance":"shashwatmdas-Predator-PH315-51","ai.device.osVersion":"Linux 4.15.0-91-generic","ai.cloud.role":"Web","ai.device.osArchitecture":"x64","ai.device.osPlatform":"linux","ai.internal.sdkVersion":"node:1.0.8"},"data":{"baseType":"EventData","baseData":{"ver":2,"properties":{"reason":"startFileSearch","type":"searchProcess","scheme":"file","common.machineId":"0368571be9af00be63ebb6f48d839834b0e7616b807d0be78a5ef4bb335361e6","sessionID":"92b4fe55-3122-4699-8e2e-2147a39150ce1591100246759","commitHash":"b37e54c98e1a74ba89e03073e5a3761284e3ffb0","version":"1.38.1","common.platformVersion":"4.15.0","common.platform":"Linux","common.nodePlatform":"linux","common.nodeArch":"x64","common.product":"desktop","timestamp":"2020-06-02T12:19:27.981Z","common.version.shell":"4.2.10","common.version.renderer":"69.0.3497.128","common.firstSessionDate":"Sun, 29 Sep 2019 23:51:46 GMT","common.lastSessionDate":"Tue, 02 Jun 2020 09:24:03 GMT","common.isNewSession":"0","common.instanceId":"319b87fd-1aa0-48b3-b0c7-882d6bc7cdb8","common.remoteAuthority":"none"},"measurements":{"resultCount":12,"workspaceFolderCount":1,"endToEndTime":105038,"fileWalkTime":102599,"directoriesWalked":0,"filesWalked":0,"cmdTime":102599,"cmdResultCount":12,"common.timesincesessionstart":121222,"common.sequence":51},"name":"monacoworkbench/searchComplete"}},"iKey":"AIF-444c3af9-8e69-4462-ab49-4191e6ad1916","name":"Microsoft.ApplicationInsights.AIF444c3af98e694462ab494191e6ad1916.Event","time":"2020-06-02T12:19:27.983Z"}
{"ver":1,"sampleRate":100,"tags":{"ai.application.ver":"1.38.1","ai.device.id":"","ai.cloud.roleInstance":"shashwatmdas-Predator-PH315-51","ai.device.osVersion":"Linux 4.15.0-91-generic","ai.cloud.role":"Web","ai.device.osArchitecture":"x64","ai.device.osPlatform":"linux","ai.internal.sdkVersion":"node:1.0.8"},"data":{"baseType":"EventData","baseData":{"ver":2,"properties":{"workspace.id":"5157280321a7c911146deaab615aec6fd2bb0c19","fileTypes":"[{\"name\":\"json\",\"count\":503},{\"name\":\"js\",\"count\":40},{\"name\":\"png\",\"count\":6},{\"name\":\"jpg\",\"count\":4},{\"name\":\"ttf\",\"count\":4},{\"name\":\"snap\",\"count\":2},{\"name\":\"BLOB\",\"count\":2},{\"name\":\"MAP\",\"count\":2},{\"name\":\"log\",\"count\":1},{\"name\":\"lock\",\"count\":1},{\"name\":\"fuse_hidden000a4e730000000d\",\"count\":1},{\"name\":\"fuse_hidden000a4e880000000c\",\"count\":1},{\"name\":\"fuse_hidden000a4e830000000a\",\"count\":1},{\"name\":\"fuse_hidden000a4e8e0000000b\",\"count\":1},{\"name\":\"cpuprofile\",\"count\":1},{\"name\":\"md\",\"count\":1},{\"name\":\"gitignore\",\"count\":1},{\"name\":\"otf\",\"count\":1}]","configTypes":"[{\"name\":\"package.json\",\"count\":1},{\"name\":\"settings.json\",\"count\":1}]","launchConfigs":"[]","common.machineId":"0368571be9af00be63ebb6f48d839834b0e7616b807d0be78a5ef4bb335361e6","sessionID":"1d0b8a89-c295-41bc-91ef-ef080d1999321591100246965","commitHash":"b37e54c98e1a74ba89e03073e5a3761284e3ffb0","version":"1.38.1","common.platformVersion":"4.15.0","common.platform":"Linux","common.nodePlatform":"linux","common.nodeArch":"x64","common.product":"desktop","timestamp":"2020-06-02T12:19:28.771Z"},"measurements":{"common.timesincesessionstart":121806,"common.sequence":2},"name":"monacoworkbench/workspace.stats"}},"iKey":"AIF-444c3af9-8e69-4462-ab49-4191e6ad1916","name":"Microsoft.ApplicationInsights.AIF444c3af98e694462ab494191e6ad1916.Event","time":"2020-06-02T12:19:28.772Z"}
{"ver":1,"sampleRate":100,"tags":{"ai.application.ver":"1.38.1","ai.device.id":"","ai.cloud.roleInstance":"shashwatmdas-Predator-PH315-51","ai.device.osVersion":"Linux 4.15.0-91-generic","ai.cloud.role":"Web","ai.device.osArchitecture":"x64","ai.device.osPlatform":"linux","ai.internal.sdkVersion":"node:1.0.8"},"data":{"baseType":"EventData","baseData":{"ver":2,"properties":{"id":"Zignd.html-css-class-completion","name":"html-css-class-completion","extensionVersion":"1.19.0","publisherDisplayName":"Zignd","activationEvents":"*","reason":"*","outcome":"success","common.machineId":"0368571be9af00be63ebb6f48d839834b0e7616b807d0be78a5ef4bb335361e6","sessionID":"92b4fe55-3122-4699-8e2e-2147a39150ce1591100246759","commitHash":"b37e54c98e1a74ba89e03073e5a3761284e3ffb0","version":"1.38.1","common.platformVersion":"4.15.0","common.platform":"Linux","common.nodePlatform":"linux","common.nodeArch":"x64","common.product":"desktop","timestamp":"2020-06-02T12:19:29.104Z","common.version.shell":"4.2.10","common.version.renderer":"69.0.3497.128","common.firstSessionDate":"Sun, 29 Sep 2019 23:51:46 GMT","common.lastSessionDate":"Tue, 02 Jun 2020 09:24:03 GMT","common.isNewSession":"0","common.instanceId":"319b87fd-1aa0-48b3-b0c7-882d6bc7cdb8","common.remoteAuthority":"none"},"measurements":{"isBuiltin":0,"startup":1,"codeLoadingTime":5042,"activateCallTime":1,"activateResolvedTime":107053,"pluginHostTelemetry":1,"common.timesincesessionstart":122345,"common.sequence":52},"name":"monacoworkbench/extensionActivationTimes"}},"iKey":"AIF-444c3af9-8e69-4462-ab49-4191e6ad1916","name":"Microsoft.ApplicationInsights.AIF444c3af98e694462ab494191e6ad1916.Event","time":"2020-06-02T12:19:29.105Z"}
{"ver":1,"sampleRate":100,"tags":{"ai.application.ver":"1.38.1","ai.device.id":"","ai.cloud.roleInstance":"shashwatmdas-Predator-PH315-51","ai.device.osVersion":"Linux 4.15.0-91-generic","ai.cloud.role":"Web","ai.device.osArchitecture":"x64","ai.device.osPlatform":"linux","ai.internal.sdkVersion":"node:1.0.8"},"data":{"baseType":"EventData","baseData":{"ver":2,"properties":{"mimeType":"text/javascript, text/plain","ext":".js","common.machineId":"0368571be9af00be63ebb6f48d839834b0e7616b807d0be78a5ef4bb335361e6","sessionID":"92b4fe55-3122-4699-8e2e-2147a39150ce1591100246759","commitHash":"b37e54c98e1a74ba89e03073e5a3761284e3ffb0","version":"1.38.1","common.platformVersion":"4.15.0","common.platform":"Linux","common.nodePlatform":"linux","common.nodeArch":"x64","common.product":"desktop","timestamp":"2020-06-02T12:19:39.380Z","common.version.shell":"4.2.10","common.version.renderer":"69.0.3497.128","common.firstSessionDate":"Sun, 29 Sep 2019 23:51:46 GMT","common.lastSessionDate":"Tue, 02 Jun 2020 09:24:03 GMT","common.isNewSession":"0","common.instanceId":"319b87fd-1aa0-48b3-b0c7-882d6bc7cdb8","common.remoteAuthority":"none"},"measurements":{"path":1224376193,"reason":3,"common.timesincesessionstart":132621,"common.sequence":53},"name":"monacoworkbench/fileGet"}},"iKey":"AIF-444c3af9-8e69-4462-ab49-4191e6ad1916","name":"Microsoft.ApplicationInsights.AIF444c3af98e694462ab494191e6ad1916.Event","time":"2020-06-02T12:19:39.381Z"}