{"ver":1,"sampleRate":100,"tags":{"ai.application.ver":"1.38.1","ai.device.id":"","ai.cloud.roleInstance":"shashwatmdas-Predator-PH315-51","ai.device.osVersion":"Linux 4.15.0-91-generic","ai.cloud.role":"Web","ai.device.osArchitecture":"x64","ai.device.osPlatform":"linux","ai.internal.sdkVersion":"node:1.0.8"},"data":{"baseType":"EventData","baseData":{"ver":2,"properties":{"id":"cursorWordEndRightSelect","from":"keybinding","common.machineId":"0368571be9af00be63ebb6f48d839834b0e7616b807d0be78a5ef4bb335361e6","sessionID":"91f6ac7f-b98a-4d1b-8612-71bfd2a514471591186461434","commitHash":"b37e54c98e1a74ba89e03073e5a3761284e3ffb0","version":"1.38.1","common.platformVersion":"4.15.0","common.platform":"Linux","common.nodePlatform":"linux","common.nodeArch":"x64","common.product":"desktop","timestamp":"2020-06-04T10:01:34.955Z","common.version.shell":"4.2.10","common.version.renderer":"69.0.3497.128","common.firstSessionDate":"Sun, 29 Sep 2019 23:51:46 GMT","common.lastSessionDate":"Tue, 02 Jun 2020 12:17:23 GMT","common.isNewSession":"0","common.instanceId":"319b87fd-1aa0-48b3-b0c7-882d6bc7cdb8","common.remoteAuthority":"none"},"measurements":{"common.timesincesessionstart":78433521,"common.sequence":3103},"name":"monacoworkbench/workbenchActionExecuted"}},"iKey":"AIF-444c3af9-8e69-4462-ab49-4191e6ad1916","name":"Microsoft.ApplicationInsights.AIF444c3af98e694462ab494191e6ad1916.Event","time":"2020-06-04T10:01:34.977Z"}
{"ver":1,"sampleRate":100,"tags":{"ai.application.ver":"1.38.1","ai.device.id":"","ai.cloud.roleInstance":"shashwatmdas-Predator-PH315-51","ai.device.osVersion":"Linux 4.15.0-91-generic","ai.cloud.role":"Web","ai.device.osArchitecture":"x64","ai.device.osPlatform":"linux","ai.internal.sdkVersion":"node:1.0.8"},"data":{"baseType":"EventData","baseData":{"ver":2,"properties":{"id":"cursorWordEndRightSelect","from":"keybinding","common.machineId":"0368571be9af00be63ebb6f48d839834b0e7616b807d0be78a5ef4bb335361e6","sessionID":"91f6ac7f-b98a-4d1b-8612-71bfd2a514471591186461434","commitHash":"b37e54c98e1a74ba89e03073e5a3761284e3ffb0","version":"1.38.1","common.platformVersion":"4.15.0","common.platform":"Linux","common.nodePlatform":"linux","common.nodeArch":"x64","common.product":"desktop","timestamp":"2020-06-04T10:01:35.127Z","common.version.shell":"4.2.10","common.version.renderer":"69.0.3497.128","common.firstSessionDate":"Sun, 29 Sep 2019 23:51:46 GMT","common.lastSessionDate":"Tue, 02 Jun 2020 12:17:23 GMT","common.isNewSession":"0","common.instanceId":"319b87fd-1aa0-48b3-b0c7-882d6bc7cdb8","common.remoteAuthority":"none"},"measurements":{"common.timesincesessionstart":78433693,"common.sequence":3104},"name":"monacoworkbench/workbenchActionExecuted"}},"iKey":"AIF-444c3af9-8e69-4462-ab49-4191e6ad1916","name":"Microsoft.ApplicationInsights.AIF444c3af98e694462ab494191e6ad1916.Event","time":"2020-06-04T10:01:35.143Z"}
{"ver":1,"sampleRate":100,"tags":{"ai.application.ver":"1.38.1","ai.device.id":"","ai.cloud.roleInstance":"shashwatmdas-Predator-PH315-51","ai.device.osVersion":"Linux 4.15.0-91-generic","ai.cloud.role":"Web","ai.device.osArchitecture":"x64","ai.device.osPlatform":"linux","ai.internal.sdkVersion":"node:1.0.8"},"data":{"baseType":"EventData","baseData":{"ver":2,"properties":{"id":"cursorWordEndRightSelect","from":"keybinding","common.machineId":"0368571be9af00be63ebb6f48d839834b0e7616b807d0be78a5ef4bb335361e6","sessionID":"91f6ac7f-b98a-4d1b-8612-71bfd2a514471591186461434","commitHash":"b37e54c98e1a74ba89e03073e5a3761284e3ffb0","version":"1.38.1","common.platformVersion":"4.15.0","common.platform":"Linux","common.nodePlatform":"linux","common.nodeArch":"x64","common.product":"desktop","timestamp":"2020-06-04T10:01:35.289Z","common.version.shell":"4.2.10","common.version.renderer":"69.0.3497.128","common.firstSessionDate":"Sun, 29 Sep 2019 23:51:46 GMT","common.lastSessionDate":"Tue, 02 Jun 2020 12:17:23 GMT","common.isNewSession":"0","common.instanceId":"319b87fd-1aa0-48b3-b0c7-882d6bc7cdb8","common.remoteAuthority":"none"},"measurements":{"common.timesincesessionstart":78433855,"common.sequence":3105},"name":"monacoworkbench/workbenchActionExecuted"}},"iKey":"AIF-444c3af9-8e69-4462-ab49-4191e6ad1916","name":"Microsoft.ApplicationInsights.AIF444c3af98e694462ab494191e6ad1916.Event","time":"2020-06-04T10:01:35.304Z"}
{"ver":1,"sampleRate":100,"tags":{"ai.application.ver":"1.38.1","ai.device.id":"","ai.cloud.roleInstance":"shashwatmdas-Predator-PH315-51","ai.device.osVersion":"Linux 4.15.0-91-generic","ai.cloud.role":"Web","ai.device.osArchitecture":"x64","ai.device.osPlatform":"linux","ai.internal.sdkVersion":"node:1.0.8"},"data":{"baseType":"EventData","baseData":{"ver":2,"properties":{"id":"cursorWordEndRightSelect","from":"keybinding","common.machineId":"0368571be9af00be63ebb6f48d839834b0e7616b807d0be78a5ef4bb335361e6","sessionID":"91f6ac7f-b98a-4d1b-8612-71bfd2a514471591186461434","commitHash":"b37e54c98e1a74ba89e03073e5a3761284e3ffb0","version":"1.38.1","common.platformVersion":"4.15.0","common.platform":"Linux","common.nodePlatform":"linux","common.nodeArch":"x64","common.product":"desktop","timestamp":"2020-06-04T10:01:35.452Z","common.version.shell":"4.2.10","common.version.renderer":"69.0.3497.128","common.firstSessionDate":"Sun, 29 Sep 2019 23:51:46 GMT","common.lastSessionDate":"Tue, 02 Jun 2020 12:17:23 GMT","common.isNewSession":"0","common.instanceId":"319b87fd-1aa0-48b3-b0c7-882d6bc7cdb8","common.remoteAuthority":"none"},"measurements":{"common.timesincesessionstart":78434018,"common.sequence":3106},"name":"monacoworkbench/workbenchActionExecuted"}},"iKey":"AIF-444c3af9-8e69-4462-ab49-4191e6ad1916","name":"Microsoft.ApplicationInsights.AIF444c3af98e694462ab494191e6ad1916.Event","time":"2020-06-04T10:01:35.467Z"}
{"ver":1,"sampleRate":100,"tags":{"ai.application.ver":"1.38.1","ai.device.id":"","ai.cloud.roleInstance":"shashwatmdas-Predator-PH315-51","ai.device.osVersion":"Linux 4.15.0-91-generic","ai.cloud.role":"Web","ai.device.osArchitecture":"x64","ai.device.osPlatform":"linux","ai.internal.sdkVersion":"node:1.0.8"},"data":{"baseType":"EventData","baseData":{"ver":2,"properties":{"id":"cursorWordEndRightSelect","from":"keybinding","common.machineId":"0368571be9af00be63ebb6f48d839834b0e7616b807d0be78a5ef4bb335361e6","sessionID":"91f6ac7f-b98a-4d1b-8612-71bfd2a514471591186461434","commitHash":"b37e54c98e1a74ba89e03073e5a3761284e3ffb0","version":"1.38.1","common.platformVersion":"4.15.0","common.platform":"Linux","common.nodePlatform":"linux","common.nodeArch":"x64","common.product":"desktop","timestamp":"2020-06-04T10:01:35.640Z","common.version.shell":"4.2.10","common.version.renderer":"69.0.3497.128","common.firstSessionDate":"Sun, 29 Sep 2019 23:51:46 GMT","common.lastSessionDate":"Tue, 02 Jun 2020 12:17:23 GMT","common.isNewSession":"0","common.instanceId":"319b87fd-1aa0-48b3-b0c7-882d6bc7cdb8","common.remoteAuthority":"none"},"measurements":{"common.timesincesessionstart":78434206,"common.sequence":3107},"name":"monacoworkbench/workbenchActionExecuted"}},"iKey":"AIF-444c3af9-8e69-4462-ab49-4191e6ad1916","name":"Microsoft.ApplicationInsights.AIF444c3af98e694462ab494191e6ad1916.Event","time":"2020-06-04T10:01:35.655Z"}
{"ver":1,"sampleRate":100,"tags":{"ai.application.ver":"1.38.1","ai.device.id":"","ai.cloud.roleInstance":"shashwatmdas-Predator-PH315-51","ai.device.osVersion":"Linux 4.15.0-91-generic","ai.cloud.role":"Web","ai.device.osArchitecture":"x64","ai.device.osPlatform":"linux","ai.internal.sdkVersion":"node:1.0.8"},"data":{"baseType":"EventData","baseData":{"ver":2,"properties":{"id":"cursorWordEndRightSelect","from":"keybinding","common.machineId":"0368571be9af00be63ebb6f48d839834b0e7616b807d0be78a5ef4bb335361e6","sessionID":"91f6ac7f-b98a-4d1b-8612-71bfd2a514471591186461434","commitHash":"b37e54c98e1a74ba89e03073e5a3761284e3ffb0","version":"1.38.1","common.platformVersion":"4.15.0","common.platform":"Linux","common.nodePlatform":"linux","common.nodeArch":"x64","common.product":"desktop","timestamp":"2020-06-04T10:01:35.816Z","common.version.shell":"4.2.10","common.version.renderer":"69.0.3497.128","common.firstSessionDate":"Sun, 29 Sep 2019 23:51:46 GMT","common.lastSessionDate":"Tue, 02 Jun 2020 12:17:23 GMT","common.isNewSession":"0","common.instanceId":"319b87fd-1aa0-48b3-b0c7-882d6bc7cdb8","common.remoteAuthority":"none"},"measurements":{"common.timesincesessionstart":78434382,"common.sequence":3108},"name":"monacoworkbench/workbenchActionExecuted"}},"iKey":"AIF-444c3af9-8e69-4462-ab49-4191e6ad1916","name":"Microsoft.ApplicationInsights.AIF444c3af98e694462ab494191e6ad1916.Event","time":"2020-06-04T10:01:35.832Z"}
{"ver":1,"sampleRate":100,"tags":{"ai.application.ver":"1.38.1","ai.device.id":"","ai.cloud.roleInstance":"shashwatmdas-Predator-PH315-51","ai.device.osVersion":"Linux 4.15.0-91-generic","ai.cloud.role":"Web","ai.device.osArchitecture":"x64","ai.device.osPlatform":"linux","ai.internal.sdkVersion":"node:1.0.8"},"data":{"baseType":"EventData","baseData":{"ver":2,"properties":{"id":"cursorWordEndRightSelect","from":"keybinding","common.machineId":"0368571be9af00be63ebb6f48d839834b0e7616b807d0be78a5ef4bb335361e6","sessionID":"91f6ac7f-b98a-4d1b-8612-71bfd2a514471591186461434","commitHash":"b37e54c98e1a74ba89e03073e5a3761284e3ffb0","version":"1.38.1","common.platformVersion":"4.15.0","common.platform":"Linux","common.nodePlatform":"linux","common.nodeArch":"x64","common.product":"desktop","timestamp":"2020-06-04T10:01:36.003Z","common.version.shell":"4.2.10","common.version.renderer":"69.0.3497.128","common.firstSessionDate":"Sun, 29 Sep 2019 23:51:46 GMT","common.lastSessionDate":"Tue, 02 Jun 2020 12:17:23 GMT","common.isNewSession":"0","common.instanceId":"319b87fd-1aa0-48b3-b0c7-882d6bc7cdb8","common.remoteAuthority":"none"},"measurements":{"common.timesincesessionstart":78434569,"common.sequence":3109},"name":"monacoworkbench/workbenchActionExecuted"}},"iKey":"AIF-444c3af9-8e69-4462-ab49-4191e6ad1916","name":"Microsoft.ApplicationInsights.AIF444c3af98e694462ab494191e6ad1916.Event","time":"2020-06-04T10:01:36.018Z"}
{"ver":1,"sampleRate":100,"tags":{"ai.application.ver":"1.38.1","ai.device.id":"","ai.cloud.roleInstance":"shashwatmdas-Predator-PH315-51","ai.device.osVersion":"Linux 4.15.0-91-generic","ai.cloud.role":"Web","ai.device.osArchitecture":"x64","ai.device.osPlatform":"linux","ai.internal.sdkVersion":"node:1.0.8"},"data":{"baseType":"EventData","baseData":{"ver":2,"properties":{"id":"cursorWordEndRightSelect","from":"keybinding","common.machineId":"0368571be9af00be63ebb6f48d839834b0e7616b807d0be78a5ef4bb335361e6","sessionID":"91f6ac7f-b98a-4d1b-8612-71bfd2a514471591186461434","commitHash":"b37e54c98e1a74ba89e03073e5a3761284e3ffb0","version":"1.38.1","common.platformVersion":"4.15.0","common.platform":"Linux","common.nodePlatform":"linux","common.nodeArch":"x64","common.product":"desktop","timestamp":"2020-06-04T10:01:36.187Z","common.version.shell":"4.2.10","common.version.renderer":"69.0.3497.128","common.firstSessionDate":"Sun, 29 Sep 2019 23:51:46 GMT","common.lastSessionDate":"Tue, 02 Jun 2020 12:17:23 GMT","common.isNewSession":"0","common.instanceId":"319b87fd-1aa0-48b3-b0c7-882d6bc7cdb8","common.remoteAuthority":"none"},"measurements":{"common.timesincesessionstart":78434753,"common.sequence":3110},"name":"monacoworkbench/workbenchActionExecuted"}},"iKey":"AIF-444c3af9-8e69-4462-ab49-4191e6ad1916","name":"Microsoft.ApplicationInsights.AIF444c3af98e694462ab494191e6ad1916.Event","time":"2020-06-04T10:01:36.195Z"}
{"ver":1,"sampleRate":100,"tags":{"ai.application.ver":"1.38.1","ai.device.id":"","ai.cloud.roleInstance":"shashwatmdas-Predator-PH315-51","ai.device.osVersion":"Linux 4.15.0-91-generic","ai.cloud.role":"Web","ai.device.osArchitecture":"x64","ai.device.osPlatform":"linux","ai.internal.sdkVersion":"node:1.0.8"},"data":{"baseType":"EventData","baseData":{"ver":2,"properties":{"id":"cursorWordEndRightSelect","from":"keybinding","common.machineId":"0368571be9af00be63ebb6f48d839834b0e7616b807d0be78a5ef4bb335361e6","sessionID":"91f6ac7f-b98a-4d1b-8612-71bfd2a514471591186461434","commitHash":"b37e54c98e1a74ba89e03073e5a3761284e3ffb0","version":"1.38.1","common.platformVersion":"4.15.0","common.platform":"Linux","common.nodePlatform":"linux","common.nodeArch":"x64","common.product":"desktop","timestamp":"2020-06-04T10:01:36.605Z","common.version.shell":"4.2.10","common.version.renderer":"69.0.3497.128","common.firstSessionDate":"Sun, 29 Sep 2019 23:51:46 GMT","common.lastSessionDate":"Tue, 02 Jun 2020 12:17:23 GMT","common.isNewSession":"0","common.instanceId":"319b87fd-1aa0-48b3-b0c7-882d6bc7cdb8","common.remoteAuthority":"none"},"measurements":{"common.timesincesessionstart":78435171,"common.sequence":3111},"name":"monacoworkbench/workbenchActionExecuted"}},"iKey":"AIF-444c3af9-8e69-4462-ab49-4191e6ad1916","name":"Microsoft.ApplicationInsights.AIF444c3af98e694462ab494191e6ad1916.Event","time":"2020-06-04T10:01:36.620Z"}
{"ver":1,"sampleRate":100,"tags":{"ai.application.ver":"1.38.1","ai.device.id":"","ai.cloud.roleInstance":"shashwatmdas-Predator-PH315-51","ai.device.osVersion":"Linux 4.15.0-91-generic","ai.cloud.role":"Web","ai.device.osArchitecture":"x64","ai.device.osPlatform":"linux","ai.internal.sdkVersion":"node:1.0.8"},"data":{"baseType":"EventData","baseData":{"ver":2,"properties":{"id":"cursorRightSelect","from":"keybinding","common.machineId":"0368571be9af00be63ebb6f48d839834b0e7616b807d0be78a5ef4bb335361e6","sessionID":"91f6ac7f-b98a-4d1b-8612-71bfd2a514471591186461434","commitHash":"b37e54c98e1a74ba89e03073e5a3761284e3ffb0","version":"1.38.1","common.platformVersion":"4.15.0","common.platform":"Linux","common.nodePlatform":"linux","common.nodeArch":"x64","common.product":"desktop","timestamp":"2020-06-04T10:01:37.036Z","common.version.shell":"4.2.10","common.version.renderer":"69.0.3497.128","common.firstSessionDate":"Sun, 29 Sep 2019 23:51:46 GMT","common.lastSessionDate":"Tue, 02 Jun 2020 12:17:23 GMT","common.isNewSession":"0","common.instanceId":"319b87fd-1aa0-48b3-b0c7-882d6bc7cdb8","common.remoteAuthority":"none"},"measurements":{"common.timesincesessionstart":78435602,"common.sequence":3112},"name":"monacoworkbench/workbenchActionExecuted"}},"iKey":"AIF-444c3af9-8e69-4462-ab49-4191e6ad1916","name":"Microsoft.ApplicationInsights.AIF444c3af98e694462ab494191e6ad1916.Event","time":"2020-06-04T10:01:37.043Z"}
{"ver":1,"sampleRate":100,"tags":{"ai.application.ver":"1.38.1","ai.device.id":"","ai.cloud.roleInstance":"shashwatmdas-Predator-PH315-51","ai.device.osVersion":"Linux 4.15.0-91-generic","ai.cloud.role":"Web","ai.device.osArchitecture":"x64","ai.device.osPlatform":"linux","ai.internal.sdkVersion":"node:1.0.8"},"data":{"baseType":"EventData","baseData":{"ver":2,"properties":{"id":"cursorRightSelect","from":"keybinding","common.machineId":"0368571be9af00be63ebb6f48d839834b0e7616b807d0be78a5ef4bb335361e6","sessionID":"91f6ac7f-b98a-4d1b-8612-71bfd2a514471591186461434","commitHash":"b37e54c98e1a74ba89e03073e5a3761284e3ffb0","version":"1.38.1","common.platformVersion":"4.15.0","common.platform":"Linux","common.nodePlatform":"linux","common.nodeArch":"x64","common.product":"desktop","timestamp":"2020-06-04T10:01:37.197Z","common.version.shell":"4.2.10","common.version.renderer":"69.0.3497.128","common.firstSessionDate":"Sun, 29 Sep 2019 23:51:46 GMT","common.lastSessionDate":"Tue, 02 Jun 2020 12:17:23 GMT","common.isNewSession":"0","common.instanceId":"319b87fd-1aa0-48b3-b0c7-882d6bc7cdb8","common.remoteAuthority":"none"},"measurements":{"common.timesincesessionstart":78435763,"common.sequence":3113},"name":"monacoworkbench/workbenchActionExecuted"}},"iKey":"AIF-444c3af9-8e69-4462-ab49-4191e6ad1916","name":"Microsoft.ApplicationInsights.AIF444c3af98e694462ab494191e6ad1916.Event","time":"2020-06-04T10:01:37.206Z"}
{"ver":1,"sampleRate":100,"tags":{"ai.application.ver":"1.38.1","ai.device.id":"","ai.cloud.roleInstance":"shashwatmdas-Predator-PH315-51","ai.device.osVersion":"Linux 4.15.0-91-generic","ai.cloud.role":"Web","ai.device.osArchitecture":"x64","ai.device.osPlatform":"linux","ai.internal.sdkVersion":"node:1.0.8"},"data":{"baseType":"EventData","baseData":{"ver":2,"properties":{"id":"cursorRightSelect","from":"keybinding","common.machineId":"0368571be9af00be63ebb6f48d839834b0e7616b807d0be78a5ef4bb335361e6","sessionID":"91f6ac7f-b98a-4d1b-8612-71bfd2a514471591186461434","commitHash":"b37e54c98e1a74ba89e03073e5a3761284e3ffb0","version":"1.38.1","common.platformVersion":"4.15.0","common.platform":"Linux","common.nodePlatform":"linux","common.nodeArch":"x64","common.product":"desktop","timestamp":"2020-06-04T10:01:37.376Z","common.version.shell":"4.2.10","common.version.renderer":"69.0.3497.128","common.firstSessionDate":"Sun, 29 Sep 2019 23:51:46 GMT","common.lastSessionDate":"Tue, 02 Jun 2020 12:17:23 GMT","common.isNewSession":"0","common.instanceId":"319b87fd-1aa0-48b3-b0c7-882d6bc7cdb8","common.remoteAuthority":"none"},"measurements":{"common.timesincesessionstart":78435942,"common.sequence":3114},"name":"monacoworkbench/workbenchActionExecuted"}},"iKey":"AIF-444c3af9-8e69-4462-ab49-4191e6ad1916","name":"Microsoft.ApplicationInsights.AIF444c3af98e694462ab494191e6ad1916.Event","time":"2020-06-04T10:01:37.392Z"}
{"ver":1,"sampleRate":100,"tags":{"ai.application.ver":"1.38.1","ai.device.id":"","ai.cloud.roleInstance":"shashwatmdas-Predator-PH315-51","ai.device.osVersion":"Linux 4.15.0-91-generic","ai.cloud.role":"Web","ai.device.osArchitecture":"x64","ai.device.osPlatform":"linux","ai.internal.sdkVersion":"node:1.0.8"},"data":{"baseType":"EventData","baseData":{"ver":2,"properties":{"id":"editor.action.clipboardCutAction","from":"keybinding","common.machineId":"0368571be9af00be63ebb6f48d839834b0e7616b807d0be78a5ef4bb335361e6","sessionID":"91f6ac7f-b98a-4d1b-8612-71bfd2a514471591186461434","commitHash":"b37e54c98e1a74ba89e03073e5a3761284e3ffb0","version":"1.38.1","common.platformVersion":"4.15.0","common.platform":"Linux","common.nodePlatform":"linux","common.nodeArch":"x64","common.product":"desktop","timestamp":"2020-06-04T10:01:38.959Z","common.version.shell":"4.2.10","common.version.renderer":"69.0.3497.128","common.firstSessionDate":"Sun, 29 Sep 2019 23:51:46 GMT","common.lastSessionDate":"Tue, 02 Jun 2020 12:17:23 GMT","common.isNewSession":"0","common.instanceId":"319b87fd-1aa0-48b3-b0c7-882d6bc7cdb8","common.remoteAuthority":"none"},"measurements":{"common.timesincesessionstart":78437525,"common.sequence":3115},"name":"monacoworkbench/workbenchActionExecuted"}},"iKey":"AIF-444c3af9-8e69-4462-ab49-4191e6ad1916","name":"Microsoft.ApplicationInsights.AIF444c3af98e694462ab494191e6ad1916.Event","time":"2020-06-04T10:01:38.961Z"}
{"ver":1,"sampleRate":100,"tags":{"ai.application.ver":"1.38.1","ai.device.id":"","ai.cloud.roleInstance":"shashwatmdas-Predator-PH315-51","ai.device.osVersion":"Linux 4.15.0-91-generic","ai.cloud.role":"Web","ai.device.osArchitecture":"x64","ai.device.osPlatform":"linux","ai.internal.sdkVersion":"node:1.0.8"},"data":{"baseType":"EventData","baseData":{"ver":2,"properties":{"name":"Cut","id":"editor.action.clipboardCutAction","common.machineId":"0368571be9af00be63ebb6f48d839834b0e7616b807d0be78a5ef4bb335361e6","sessionID":"91f6ac7f-b98a-4d1b-8612-71bfd2a514471591186461434","commitHash":"b37e54c98e1a74ba89e03073e5a3761284e3ffb0","version":"1.38.1","common.platformVersion":"4.15.0","common.platform":"Linux","common.nodePlatform":"linux","common.nodeArch":"x64","common.product":"desktop","timestamp":"2020-06-04T10:01:38.959Z","common.version.shell":"4.2.10","common.version.renderer":"69.0.3497.128","common.firstSessionDate":"Sun, 29 Sep 2019 23:51:46 GMT","common.lastSessionDate":"Tue, 02 Jun 2020 12:17:23 GMT","common.isNewSession":"0","common.instanceId":"319b87fd-1aa0-48b3-b0c7-882d6bc7cdb8","common.remoteAuthority":"none"},"measurements":{"common.timesincesessionstart":78437525,"common.sequence":3116},"name":"monacoworkbench/editorActionInvoked"}},"iKey":"AIF-444c3af9-8e69-4462-ab49-4191e6ad1916","name":"Microsoft.ApplicationInsights.AIF444c3af98e694462ab494191e6ad1916.Event","time":"2020-06-04T10:01:38.961Z"}
{"ver":1,"sampleRate":100,"tags":{"ai.application.ver":"1.38.1","ai.device.id":"","ai.cloud.roleInstance":"shashwatmdas-Predator-PH315-51","ai.device.osVersion":"Linux 4.15.0-91-generic","ai.cloud.role":"Web","ai.device.osArchitecture":"x64","ai.device.osPlatform":"linux","ai.internal.sdkVersion":"node:1.0.8"},"data":{"baseType":"EventData","baseData":{"ver":2,"properties":{"id":"workbench.action.files.save","from":"keybinding","common.machineId":"0368571be9af00be63ebb6f48d839834b0e7616b807d0be78a5ef4bb335361e6","sessionID":"91f6ac7f-b98a-4d1b-8612-71bfd2a514471591186461434","commitHash":"b37e54c98e1a74ba89e03073e5a3761284e3ffb0","version":"1.38.1","common.platformVersion":"4.15.0","common.platform":"Linux","common.nodePlatform":"linux","common.nodeArch":"x64","common.product":"desktop","timestamp":"2020-06-04T10:01:39.225Z","common.version.shell":"4.2.10","common.version.renderer":"69.0.3497.128","common.firstSessionDate":"Sun, 29 Sep 2019 23:51:46 GMT","common.lastSessionDate":"Tue, 02 Jun 2020 12:17:23 GMT","common.isNewSession":"0","common.instanceId":"319b87fd-1aa0-48b3-b0c7-882d6bc7cdb8","common.remoteAuthority":"none"},"measurements":{"common.timesincesessionstart":78437791,"common.sequence":3117},"name":"monacoworkbench/workbenchActionExecuted"}},"iKey":"AIF-444c3af9-8e69-4462-ab49-4191e6ad1916","name":"Microsoft.ApplicationInsights.AIF444c3af98e694462ab494191e6ad1916.Event","time":"2020-06-04T10:01:39.226Z"}
{"ver":1,"sampleRate":100,"tags":{"ai.application.ver":"1.38.1","ai.device.id":"","ai.cloud.roleInstance":"shashwatmdas-Predator-PH315-51","ai.device.osVersion":"Linux 4.15.0-91-generic","ai.cloud.role":"Web","ai.device.osArchitecture":"x64","ai.device.osPlatform":"linux","ai.internal.sdkVersion":"node:1.0.8"},"data":{"baseType":"EventData","baseData":{"ver":2,"properties":{"mimeType":"text/javascript, text/plain","ext":".js","common.machineId":"0368571be9af00be63ebb6f48d839834b0e7616b807d0be78a5ef4bb335361e6","sessionID":"91f6ac7f-b98a-4d1b-8612-71bfd2a514471591186461434","commitHash":"b37e54c98e1a74ba89e03073e5a3761284e3ffb0","version":"1.38.1","common.platformVersion":"4.15.0","common.platform":"Linux","common.nodePlatform":"linux","common.nodeArch":"x64","common.product":"desktop","timestamp":"2020-06-04T10:01:39.371Z","common.version.shell":"4.2.10","common.version.renderer":"69.0.3497.128","common.firstSessionDate":"Sun, 29 Sep 2019 23:51:46 GMT","common.lastSessionDate":"Tue, 02 Jun 2020 12:17:23 GMT","common.isNewSession":"0","common.instanceId":"319b87fd-1aa0-48b3-b0c7-882d6bc7cdb8","common.remoteAuthority":"none"},"measurements":{"path":895052448,"reason":1,"common.timesincesessionstart":78437937,"common.sequence":3118},"name":"monacoworkbench/filePUT"}},"iKey":"AIF-444c3af9-8e69-4462-ab49-4191e6ad1916","name":"Microsoft.ApplicationInsights.AIF444c3af98e694462ab494191e6ad1916.Event","time":"2020-06-04T10:01:39.373Z"}