{"ver":1,"sampleRate":100,"tags":{"ai.application.ver":"1.38.1","ai.device.id":"","ai.cloud.roleInstance":"shashwatmdas-Predator-PH315-51","ai.device.osVersion":"Linux 4.15.0-91-generic","ai.cloud.role":"Web","ai.device.osArchitecture":"x64","ai.device.osPlatform":"linux","ai.internal.sdkVersion":"node:1.0.8"},"data":{"baseType":"EventData","baseData":{"ver":2,"properties":{"mimeType":"text/x-typescript, text/plain","ext":".ts","common.machineId":"0368571be9af00be63ebb6f48d839834b0e7616b807d0be78a5ef4bb335361e6","sessionID":"91f6ac7f-b98a-4d1b-8612-71bfd2a514471591186461434","commitHash":"b37e54c98e1a74ba89e03073e5a3761284e3ffb0","version":"1.38.1","common.platformVersion":"4.15.0","common.platform":"Linux","common.nodePlatform":"linux","common.nodeArch":"x64","common.product":"desktop","timestamp":"2020-06-03T13:54:20.047Z","common.version.shell":"4.2.10","common.version.renderer":"69.0.3497.128","common.firstSessionDate":"Sun, 29 Sep 2019 23:51:46 GMT","common.lastSessionDate":"Tue, 02 Jun 2020 12:17:23 GMT","common.isNewSession":"0","common.instanceId":"319b87fd-1aa0-48b3-b0c7-882d6bc7cdb8","common.remoteAuthority":"none"},"measurements":{"path":-327885863,"reason":2,"common.timesincesessionstart":5998613,"common.sequence":584},"name":"monacoworkbench/fileGet"}},"iKey":"AIF-444c3af9-8e69-4462-ab49-4191e6ad1916","name":"Microsoft.ApplicationInsights.AIF444c3af98e694462ab494191e6ad1916.Event","time":"2020-06-03T13:54:20.052Z"}
{"ver":1,"sampleRate":100,"tags":{"ai.application.ver":"1.38.1","ai.device.id":"","ai.cloud.roleInstance":"shashwatmdas-Predator-PH315-51","ai.device.osVersion":"Linux 4.15.0-91-generic","ai.cloud.role":"Web","ai.device.osArchitecture":"x64","ai.device.osPlatform":"linux","ai.internal.sdkVersion":"node:1.0.8"},"data":{"baseType":"EventData","baseData":{"ver":2,"properties":{"id":"deleteWordLeft","from":"keybinding","common.machineId":"0368571be9af00be63ebb6f48d839834b0e7616b807d0be78a5ef4bb335361e6","sessionID":"91f6ac7f-b98a-4d1b-8612-71bfd2a514471591186461434","commitHash":"b37e54c98e1a74ba89e03073e5a3761284e3ffb0","version":"1.38.1","common.platformVersion":"4.15.0","common.platform":"Linux","common.nodePlatform":"linux","common.nodeArch":"x64","common.product":"desktop","timestamp":"2020-06-03T13:54:20.177Z","common.version.shell":"4.2.10","common.version.renderer":"69.0.3497.128","common.firstSessionDate":"Sun, 29 Sep 2019 23:51:46 GMT","common.lastSessionDate":"Tue, 02 Jun 2020 12:17:23 GMT","common.isNewSession":"0","common.instanceId":"319b87fd-1aa0-48b3-b0c7-882d6bc7cdb8","common.remoteAuthority":"none"},"measurements":{"common.timesincesessionstart":5998743,"common.sequence":585},"name":"monacoworkbench/workbenchActionExecuted"}},"iKey":"AIF-444c3af9-8e69-4462-ab49-4191e6ad1916","name":"Microsoft.ApplicationInsights.AIF444c3af98e694462ab494191e6ad1916.Event","time":"2020-06-03T13:54:20.178Z"}
{"ver":1,"sampleRate":100,"tags":{"ai.application.ver":"1.38.1","ai.device.id":"","ai.cloud.roleInstance":"shashwatmdas-Predator-PH315-51","ai.device.osVersion":"Linux 4.15.0-91-generic","ai.cloud.role":"Web","ai.device.osArchitecture":"x64","ai.device.osPlatform":"linux","ai.internal.sdkVersion":"node:1.0.8"},"data":{"baseType":"EventData","baseData":{"ver":2,"properties":{"common.machineId":"0368571be9af00be63ebb6f48d839834b0e7616b807d0be78a5ef4bb335361e6","sessionID":"91f6ac7f-b98a-4d1b-8612-71bfd2a514471591186461434","commitHash":"b37e54c98e1a74ba89e03073e5a3761284e3ffb0","version":"1.38.1","common.platformVersion":"4.15.0","common.platform":"Linux","common.nodePlatform":"linux","common.nodeArch":"x64","common.product":"desktop","timestamp":"2020-06-03T13:54:20.913Z","common.version.shell":"4.2.10","common.version.renderer":"69.0.3497.128","common.firstSessionDate":"Sun, 29 Sep 2019 23:51:46 GMT","common.lastSessionDate":"Tue, 02 Jun 2020 12:17:23 GMT","common.isNewSession":"0","common.instanceId":"319b87fd-1aa0-48b3-b0c7-882d6bc7cdb8","common.remoteAuthority":"none"},"measurements":{"suggestionCount":32,"snippetCount":16,"textCount":16,"wasAutomaticallyTriggered":1,"common.timesincesessionstart":5999479,"common.sequence":586},"name":"monacoworkbench/suggestWidget"}},"iKey":"AIF-444c3af9-8e69-4462-ab49-4191e6ad1916","name":"Microsoft.ApplicationInsights.AIF444c3af98e694462ab494191e6ad1916.Event","time":"2020-06-03T13:54:20.928Z"}
{"ver":1,"sampleRate":100,"tags":{"ai.application.ver":"1.38.1","ai.device.id":"","ai.cloud.roleInstance":"shashwatmdas-Predator-PH315-51","ai.device.osVersion":"Linux 4.15.0-91-generic","ai.cloud.role":"Web","ai.device.osArchitecture":"x64","ai.device.osPlatform":"linux","ai.internal.sdkVersion":"node:1.0.8"},"data":{"baseType":"EventData","baseData":{"ver":2,"properties":{"id":"actions.find","from":"keybinding","common.machineId":"0368571be9af00be63ebb6f48d839834b0e7616b807d0be78a5ef4bb335361e6","sessionID":"91f6ac7f-b98a-4d1b-8612-71bfd2a514471591186461434","commitHash":"b37e54c98e1a74ba89e03073e5a3761284e3ffb0","version":"1.38.1","common.platformVersion":"4.15.0","common.platform":"Linux","common.nodePlatform":"linux","common.nodeArch":"x64","common.product":"desktop","timestamp":"2020-06-03T13:54:22.210Z","common.version.shell":"4.2.10","common.version.renderer":"69.0.3497.128","common.firstSessionDate":"Sun, 29 Sep 2019 23:51:46 GMT","common.lastSessionDate":"Tue, 02 Jun 2020 12:17:23 GMT","common.isNewSession":"0","common.instanceId":"319b87fd-1aa0-48b3-b0c7-882d6bc7cdb8","common.remoteAuthority":"none"},"measurements":{"common.timesincesessionstart":6000776,"common.sequence":587},"name":"monacoworkbench/workbenchActionExecuted"}},"iKey":"AIF-444c3af9-8e69-4462-ab49-4191e6ad1916","name":"Microsoft.ApplicationInsights.AIF444c3af98e694462ab494191e6ad1916.Event","time":"2020-06-03T13:54:22.219Z"}
{"ver":1,"sampleRate":100,"tags":{"ai.application.ver":"1.38.1","ai.device.id":"","ai.cloud.roleInstance":"shashwatmdas-Predator-PH315-51","ai.device.osVersion":"Linux 4.15.0-91-generic","ai.cloud.role":"Web","ai.device.osArchitecture":"x64","ai.device.osPlatform":"linux","ai.internal.sdkVersion":"node:1.0.8"},"data":{"baseType":"EventData","baseData":{"ver":2,"properties":{"name":"Find","id":"actions.find","common.machineId":"0368571be9af00be63ebb6f48d839834b0e7616b807d0be78a5ef4bb335361e6","sessionID":"91f6ac7f-b98a-4d1b-8612-71bfd2a514471591186461434","commitHash":"b37e54c98e1a74ba89e03073e5a3761284e3ffb0","version":"1.38.1","common.platformVersion":"4.15.0","common.platform":"Linux","common.nodePlatform":"linux","common.nodeArch":"x64","common.product":"desktop","timestamp":"2020-06-03T13:54:22.210Z","common.version.shell":"4.2.10","common.version.renderer":"69.0.3497.128","common.firstSessionDate":"Sun, 29 Sep 2019 23:51:46 GMT","common.lastSessionDate":"Tue, 02 Jun 2020 12:17:23 GMT","common.isNewSession":"0","common.instanceId":"319b87fd-1aa0-48b3-b0c7-882d6bc7cdb8","common.remoteAuthority":"none"},"measurements":{"common.timesincesessionstart":6000776,"common.sequence":588},"name":"monacoworkbench/editorActionInvoked"}},"iKey":"AIF-444c3af9-8e69-4462-ab49-4191e6ad1916","name":"Microsoft.ApplicationInsights.AIF444c3af98e694462ab494191e6ad1916.Event","time":"2020-06-03T13:54:22.220Z"}
{"ver":1,"sampleRate":100,"tags":{"ai.application.ver":"1.38.1","ai.device.id":"","ai.cloud.roleInstance":"shashwatmdas-Predator-PH315-51","ai.device.osVersion":"Linux 4.15.0-91-generic","ai.cloud.role":"Web","ai.device.osArchitecture":"x64","ai.device.osPlatform":"linux","ai.internal.sdkVersion":"node:1.0.8"},"data":{"baseType":"EventData","baseData":{"ver":2,"properties":{"id":"cursorLeft","from":"keybinding","common.machineId":"0368571be9af00be63ebb6f48d839834b0e7616b807d0be78a5ef4bb335361e6","sessionID":"91f6ac7f-b98a-4d1b-8612-71bfd2a514471591186461434","commitHash":"b37e54c98e1a74ba89e03073e5a3761284e3ffb0","version":"1.38.1","common.platformVersion":"4.15.0","common.platform":"Linux","common.nodePlatform":"linux","common.nodeArch":"x64","common.product":"desktop","timestamp":"2020-06-03T13:54:26.292Z","common.version.shell":"4.2.10","common.version.renderer":"69.0.3497.128","common.firstSessionDate":"Sun, 29 Sep 2019 23:51:46 GMT","common.lastSessionDate":"Tue, 02 Jun 2020 12:17:23 GMT","common.isNewSession":"0","common.instanceId":"319b87fd-1aa0-48b3-b0c7-882d6bc7cdb8","common.remoteAuthority":"none"},"measurements":{"common.timesincesessionstart":6004858,"common.sequence":589},"name":"monacoworkbench/workbenchActionExecuted"}},"iKey":"AIF-444c3af9-8e69-4462-ab49-4191e6ad1916","name":"Microsoft.ApplicationInsights.AIF444c3af98e694462ab494191e6ad1916.Event","time":"2020-06-03T13:54:26.301Z"}
{"ver":1,"sampleRate":100,"tags":{"ai.application.ver":"1.38.1","ai.device.id":"","ai.cloud.roleInstance":"shashwatmdas-Predator-PH315-51","ai.device.osVersion":"Linux 4.15.0-91-generic","ai.cloud.role":"Web","ai.device.osArchitecture":"x64","ai.device.osPlatform":"linux","ai.internal.sdkVersion":"node:1.0.8"},"data":{"baseType":"EventData","baseData":{"ver":2,"properties":{"id":"cursorRight","from":"keybinding","common.machineId":"0368571be9af00be63ebb6f48d839834b0e7616b807d0be78a5ef4bb335361e6","sessionID":"91f6ac7f-b98a-4d1b-8612-71bfd2a514471591186461434","commitHash":"b37e54c98e1a74ba89e03073e5a3761284e3ffb0","version":"1.38.1","common.platformVersion":"4.15.0","common.platform":"Linux","common.nodePlatform":"linux","common.nodeArch":"x64","common.product":"desktop","timestamp":"2020-06-03T13:54:26.548Z","common.version.shell":"4.2.10","common.version.renderer":"69.0.3497.128","common.firstSessionDate":"Sun, 29 Sep 2019 23:51:46 GMT","common.lastSessionDate":"Tue, 02 Jun 2020 12:17:23 GMT","common.isNewSession":"0","common.instanceId":"319b87fd-1aa0-48b3-b0c7-882d6bc7cdb8","common.remoteAuthority":"none"},"measurements":{"common.timesincesessionstart":6005114,"common.sequence":590},"name":"monacoworkbench/workbenchActionExecuted"}},"iKey":"AIF-444c3af9-8e69-4462-ab49-4191e6ad1916","name":"Microsoft.ApplicationInsights.AIF444c3af98e694462ab494191e6ad1916.Event","time":"2020-06-03T13:54:26.549Z"}
{"ver":1,"sampleRate":100,"tags":{"ai.application.ver":"1.38.1","ai.device.id":"","ai.cloud.roleInstance":"shashwatmdas-Predator-PH315-51","ai.device.osVersion":"Linux 4.15.0-91-generic","ai.cloud.role":"Web","ai.device.osArchitecture":"x64","ai.device.osPlatform":"linux","ai.internal.sdkVersion":"node:1.0.8"},"data":{"baseType":"EventData","baseData":{"ver":2,"properties":{"id":"deleteWordLeft","from":"keybinding","common.machineId":"0368571be9af00be63ebb6f48d839834b0e7616b807d0be78a5ef4bb335361e6","sessionID":"91f6ac7f-b98a-4d1b-8612-71bfd2a514471591186461434","commitHash":"b37e54c98e1a74ba89e03073e5a3761284e3ffb0","version":"1.38.1","common.platformVersion":"4.15.0","common.platform":"Linux","common.nodePlatform":"linux","common.nodeArch":"x64","common.product":"desktop","timestamp":"2020-06-03T13:54:26.864Z","common.version.shell":"4.2.10","common.version.renderer":"69.0.3497.128","common.firstSessionDate":"Sun, 29 Sep 2019 23:51:46 GMT","common.lastSessionDate":"Tue, 02 Jun 2020 12:17:23 GMT","common.isNewSession":"0","common.instanceId":"319b87fd-1aa0-48b3-b0c7-882d6bc7cdb8","common.remoteAuthority":"none"},"measurements":{"common.timesincesessionstart":6005430,"common.sequence":591},"name":"monacoworkbench/workbenchActionExecuted"}},"iKey":"AIF-444c3af9-8e69-4462-ab49-4191e6ad1916","name":"Microsoft.ApplicationInsights.AIF444c3af98e694462ab494191e6ad1916.Event","time":"2020-06-03T13:54:26.866Z"}
{"ver":1,"sampleRate":100,"tags":{"ai.application.ver":"1.38.1","ai.device.id":"","ai.cloud.roleInstance":"shashwatmdas-Predator-PH315-51","ai.device.osVersion":"Linux 4.15.0-91-generic","ai.cloud.role":"Web","ai.device.osArchitecture":"x64","ai.device.osPlatform":"linux","ai.internal.sdkVersion":"node:1.0.8"},"data":{"baseType":"EventData","baseData":{"ver":2,"properties":{"common.machineId":"0368571be9af00be63ebb6f48d839834b0e7616b807d0be78a5ef4bb335361e6","sessionID":"91f6ac7f-b98a-4d1b-8612-71bfd2a514471591186461434","commitHash":"b37e54c98e1a74ba89e03073e5a3761284e3ffb0","version":"1.38.1","common.platformVersion":"4.15.0","common.platform":"Linux","common.nodePlatform":"linux","common.nodeArch":"x64","common.product":"desktop","timestamp":"2020-06-03T13:54:27.930Z","common.version.shell":"4.2.10","common.version.renderer":"69.0.3497.128","common.firstSessionDate":"Sun, 29 Sep 2019 23:51:46 GMT","common.lastSessionDate":"Tue, 02 Jun 2020 12:17:23 GMT","common.isNewSession":"0","common.instanceId":"319b87fd-1aa0-48b3-b0c7-882d6bc7cdb8","common.remoteAuthority":"none"},"measurements":{"suggestionCount":4,"snippetCount":0,"textCount":1,"wasAutomaticallyTriggered":1,"common.timesincesessionstart":6006496,"common.sequence":592},"name":"monacoworkbench/suggestWidget"}},"iKey":"AIF-444c3af9-8e69-4462-ab49-4191e6ad1916","name":"Microsoft.ApplicationInsights.AIF444c3af98e694462ab494191e6ad1916.Event","time":"2020-06-03T13:54:27.930Z"}
{"ver":1,"sampleRate":100,"tags":{"ai.application.ver":"1.38.1","ai.device.id":"","ai.cloud.roleInstance":"shashwatmdas-Predator-PH315-51","ai.device.osVersion":"Linux 4.15.0-91-generic","ai.cloud.role":"Web","ai.device.osArchitecture":"x64","ai.device.osPlatform":"linux","ai.internal.sdkVersion":"node:1.0.8"},"data":{"baseType":"EventData","baseData":{"ver":2,"properties":{"id":"actions.find","from":"keybinding","common.machineId":"0368571be9af00be63ebb6f48d839834b0e7616b807d0be78a5ef4bb335361e6","sessionID":"91f6ac7f-b98a-4d1b-8612-71bfd2a514471591186461434","commitHash":"b37e54c98e1a74ba89e03073e5a3761284e3ffb0","version":"1.38.1","common.platformVersion":"4.15.0","common.platform":"Linux","common.nodePlatform":"linux","common.nodeArch":"x64","common.product":"desktop","timestamp":"2020-06-03T13:54:29.871Z","common.version.shell":"4.2.10","common.version.renderer":"69.0.3497.128","common.firstSessionDate":"Sun, 29 Sep 2019 23:51:46 GMT","common.lastSessionDate":"Tue, 02 Jun 2020 12:17:23 GMT","common.isNewSession":"0","common.instanceId":"319b87fd-1aa0-48b3-b0c7-882d6bc7cdb8","common.remoteAuthority":"none"},"measurements":{"common.timesincesessionstart":6008437,"common.sequence":593},"name":"monacoworkbench/workbenchActionExecuted"}},"iKey":"AIF-444c3af9-8e69-4462-ab49-4191e6ad1916","name":"Microsoft.ApplicationInsights.AIF444c3af98e694462ab494191e6ad1916.Event","time":"2020-06-03T13:54:29.894Z"}
{"ver":1,"sampleRate":100,"tags":{"ai.application.ver":"1.38.1","ai.device.id":"","ai.cloud.roleInstance":"shashwatmdas-Predator-PH315-51","ai.device.osVersion":"Linux 4.15.0-91-generic","ai.cloud.role":"Web","ai.device.osArchitecture":"x64","ai.device.osPlatform":"linux","ai.internal.sdkVersion":"node:1.0.8"},"data":{"baseType":"EventData","baseData":{"ver":2,"properties":{"name":"Find","id":"actions.find","common.machineId":"0368571be9af00be63ebb6f48d839834b0e7616b807d0be78a5ef4bb335361e6","sessionID":"91f6ac7f-b98a-4d1b-8612-71bfd2a514471591186461434","commitHash":"b37e54c98e1a74ba89e03073e5a3761284e3ffb0","version":"1.38.1","common.platformVersion":"4.15.0","common.platform":"Linux","common.nodePlatform":"linux","common.nodeArch":"x64","common.product":"desktop","timestamp":"2020-06-03T13:54:29.871Z","common.version.shell":"4.2.10","common.version.renderer":"69.0.3497.128","common.firstSessionDate":"Sun, 29 Sep 2019 23:51:46 GMT","common.lastSessionDate":"Tue, 02 Jun 2020 12:17:23 GMT","common.isNewSession":"0","common.instanceId":"319b87fd-1aa0-48b3-b0c7-882d6bc7cdb8","common.remoteAuthority":"none"},"measurements":{"common.timesincesessionstart":6008437,"common.sequence":594},"name":"monacoworkbench/editorActionInvoked"}},"iKey":"AIF-444c3af9-8e69-4462-ab49-4191e6ad1916","name":"Microsoft.ApplicationInsights.AIF444c3af98e694462ab494191e6ad1916.Event","time":"2020-06-03T13:54:29.894Z"}
{"ver":1,"sampleRate":100,"tags":{"ai.application.ver":"1.38.1","ai.device.id":"","ai.cloud.roleInstance":"shashwatmdas-Predator-PH315-51","ai.device.osVersion":"Linux 4.15.0-91-generic","ai.cloud.role":"Web","ai.device.osArchitecture":"x64","ai.device.osPlatform":"linux","ai.internal.sdkVersion":"node:1.0.8"},"data":{"baseType":"EventData","baseData":{"ver":2,"properties":{"id":"editor.action.nextMatchFindAction","from":"keybinding","common.machineId":"0368571be9af00be63ebb6f48d839834b0e7616b807d0be78a5ef4bb335361e6","sessionID":"91f6ac7f-b98a-4d1b-8612-71bfd2a514471591186461434","commitHash":"b37e54c98e1a74ba89e03073e5a3761284e3ffb0","version":"1.38.1","common.platformVersion":"4.15.0","common.platform":"Linux","common.nodePlatform":"linux","common.nodeArch":"x64","common.product":"desktop","timestamp":"2020-06-03T13:54:30.337Z","common.version.shell":"4.2.10","common.version.renderer":"69.0.3497.128","common.firstSessionDate":"Sun, 29 Sep 2019 23:51:46 GMT","common.lastSessionDate":"Tue, 02 Jun 2020 12:17:23 GMT","common.isNewSession":"0","common.instanceId":"319b87fd-1aa0-48b3-b0c7-882d6bc7cdb8","common.remoteAuthority":"none"},"measurements":{"common.timesincesessionstart":6008903,"common.sequence":595},"name":"monacoworkbench/workbenchActionExecuted"}},"iKey":"AIF-444c3af9-8e69-4462-ab49-4191e6ad1916","name":"Microsoft.ApplicationInsights.AIF444c3af98e694462ab494191e6ad1916.Event","time":"2020-06-03T13:54:30.354Z"}
{"ver":1,"sampleRate":100,"tags":{"ai.application.ver":"1.38.1","ai.device.id":"","ai.cloud.roleInstance":"shashwatmdas-Predator-PH315-51","ai.device.osVersion":"Linux 4.15.0-91-generic","ai.cloud.role":"Web","ai.device.osArchitecture":"x64","ai.device.osPlatform":"linux","ai.internal.sdkVersion":"node:1.0.8"},"data":{"baseType":"EventData","baseData":{"ver":2,"properties":{"name":"Find Next","id":"editor.action.nextMatchFindAction","common.machineId":"0368571be9af00be63ebb6f48d839834b0e7616b807d0be78a5ef4bb335361e6","sessionID":"91f6ac7f-b98a-4d1b-8612-71bfd2a514471591186461434","commitHash":"b37e54c98e1a74ba89e03073e5a3761284e3ffb0","version":"1.38.1","common.platformVersion":"4.15.0","common.platform":"Linux","common.nodePlatform":"linux","common.nodeArch":"x64","common.product":"desktop","timestamp":"2020-06-03T13:54:30.337Z","common.version.shell":"4.2.10","common.version.renderer":"69.0.3497.128","common.firstSessionDate":"Sun, 29 Sep 2019 23:51:46 GMT","common.lastSessionDate":"Tue, 02 Jun 2020 12:17:23 GMT","common.isNewSession":"0","common.instanceId":"319b87fd-1aa0-48b3-b0c7-882d6bc7cdb8","common.remoteAuthority":"none"},"measurements":{"common.timesincesessionstart":6008903,"common.sequence":596},"name":"monacoworkbench/editorActionInvoked"}},"iKey":"AIF-444c3af9-8e69-4462-ab49-4191e6ad1916","name":"Microsoft.ApplicationInsights.AIF444c3af98e694462ab494191e6ad1916.Event","time":"2020-06-03T13:54:30.354Z"}